omnibot_receiver/__init__.py
omnibot_receiver/response.py
omnibot_receiver/router.py
omnibot_receiver-3.1.6.dist-info/LICENSE
omnibot_receiver-3.1.6.dist-info/METADATA
omnibot_receiver-3.1.6.dist-info/NOTICE
omnibot_receiver-3.1.6.dist-info/WHEEL
omnibot_receiver-3.1.6.dist-info/top_level.txt
omnibot_receiver-3.1.6.dist-info/RECORD
