Metadata-Version: 2.1
Name: omnibot-receiver
Version: 3.1.6
Summary: Library for use by services that receive messages from omnibot.
Home-page: https://www.github.com/lyft/python-omnibot-receiver
Maintainer: Lyft
Maintainer-email: rlane@lyft.com
License: apache2
License-File: LICENSE
License-File: NOTICE
